{
  "flash_point": {
    "terminalPhase": "level_complete",
    "reports": [
      {
        "spawned": 10,
        "killed": 10,
        "breached": 0,
        "coreDamage": 0,
        "damageDealt": 850.0000000000002,
        "reactions": 21.368910379761754,
        "combustionFlashes": 6,
        "peakHazard": 2.6963891759142733,
        "matterHarvested": 50,
        "fieldDamageAbsorbed": 0,
        "reagentEmitted": 0,
        "armorTransitions": 0,
        "protectedAllySeconds": 0,
        "damageByChannel": {
          "atmosphere": 0,
          "corrosion": 0,
          "heat": 35.181704366087196,
          "pressure": 814.818295633913,
          "radiation": 0
        },
        "damageBySource": {
          "atmospheric_exposure": 0,
          "surface_corrosion": 0,
          "thermal_exposure": 3.69347079147832,
          "catastrophic_overpressure": 0,
          "radiation_field": 0,
          "hydrogen_oxygen_combustion": 846.3065292085219
        },
        "killsBySource": {
          "atmospheric_exposure": 0,
          "surface_corrosion": 0,
          "thermal_exposure": 0,
          "catastrophic_overpressure": 0,
          "radiation_field": 0,
          "hydrogen_oxygen_combustion": 10
        },
        "levelId": "flash_point",
        "round": 1
      },
      {
        "spawned": 7,
        "killed": 7,
        "breached": 0,
        "coreDamage": 0,
        "damageDealt": 444.9999999999999,
        "reactions": 15.183745877813637,
        "combustionFlashes": 6,
        "peakHazard": 3.287290268546837,
        "matterHarvested": 35,
        "fieldDamageAbsorbed": 0,
        "reagentEmitted": 0,
        "armorTransitions": 0,
        "protectedAllySeconds": 0,
        "damageByChannel": {
          "atmosphere": 0,
          "corrosion": 0,
          "heat": 28.708692238307336,
          "pressure": 416.2913077616926,
          "radiation": 0
        },
        "damageBySource": {
          "atmospheric_exposure": 0,
          "surface_corrosion": 0,
          "thermal_exposure": 17.247017178544468,
          "catastrophic_overpressure": 0,
          "radiation_field": 0,
          "hydrogen_oxygen_combustion": 427.7529828214555
        },
        "killsBySource": {
          "atmospheric_exposure": 0,
          "surface_corrosion": 0,
          "thermal_exposure": 0,
          "catastrophic_overpressure": 0,
          "radiation_field": 0,
          "hydrogen_oxygen_combustion": 7
        },
        "levelId": "flash_point",
        "round": 2
      },
      {
        "spawned": 18,
        "killed": 18,
        "breached": 0,
        "coreDamage": 0,
        "damageDealt": 2276.455884999998,
        "reactions": 61.00673607293778,
        "combustionFlashes": 35,
        "peakHazard": 7.968939185183967,
        "matterHarvested": 126,
        "fieldDamageAbsorbed": 0,
        "reagentEmitted": 0,
        "armorTransitions": 0,
        "protectedAllySeconds": 0,
        "damageByChannel": {
          "atmosphere": 0,
          "corrosion": 0,
          "heat": 248.9012230566887,
          "pressure": 2027.5546619433119,
          "radiation": 0
        },
        "damageBySource": {
          "atmospheric_exposure": 0,
          "surface_corrosion": 0,
          "thermal_exposure": 188.58636520192422,
          "catastrophic_overpressure": 0,
          "radiation_field": 0,
          "hydrogen_oxygen_combustion": 2087.8695197980765
        },
        "killsBySource": {
          "atmospheric_exposure": 0,
          "surface_corrosion": 0,
          "thermal_exposure": 0,
          "catastrophic_overpressure": 0,
          "radiation_field": 0,
          "hydrogen_oxygen_combustion": 18
        },
        "levelId": "flash_point",
        "round": 3
      },
      {
        "spawned": 21,
        "killed": 21,
        "breached": 0,
        "coreDamage": 0,
        "damageDealt": 3091.0550640200127,
        "reactions": 36.955185745531296,
        "combustionFlashes": 23,
        "peakHazard": 15.313249581322989,
        "matterHarvested": 175,
        "fieldDamageAbsorbed": 0,
        "reagentEmitted": 0,
        "armorTransitions": 0,
        "protectedAllySeconds": 0,
        "damageByChannel": {
          "atmosphere": 0,
          "corrosion": 0,
          "heat": 488.1617056291824,
          "pressure": 2602.8933583908192,
          "radiation": 0
        },
        "damageBySource": {
          "atmospheric_exposure": 0,
          "surface_corrosion": 0,
          "thermal_exposure": 412.1187238615657,
          "catastrophic_overpressure": 0,
          "radiation_field": 0,
          "hydrogen_oxygen_combustion": 2678.9363401584355
        },
        "killsBySource": {
          "atmospheric_exposure": 0,
          "surface_corrosion": 0,
          "thermal_exposure": 0,
          "catastrophic_overpressure": 0,
          "radiation_field": 0,
          "hydrogen_oxygen_combustion": 21
        },
        "levelId": "flash_point",
        "round": 4
      },
      {
        "spawned": 28,
        "killed": 28,
        "breached": 0,
        "coreDamage": 0,
        "damageDealt": 4684.538752299991,
        "reactions": 53.52771857789685,
        "combustionFlashes": 33,
        "peakHazard": 21.381354985140923,
        "matterHarvested": 246,
        "fieldDamageAbsorbed": 0,
        "reagentEmitted": 0,
        "armorTransitions": 0,
        "protectedAllySeconds": 0,
        "damageByChannel": {
          "atmosphere": 0,
          "corrosion": 0,
          "heat": 877.3745665822792,
          "pressure": 3807.164185717725,
          "radiation": 0
        },
        "damageBySource": {
          "atmospheric_exposure": 0,
          "surface_corrosion": 0,
          "thermal_exposure": 788.5223549366285,
          "catastrophic_overpressure": 0,
          "radiation_field": 0,
          "hydrogen_oxygen_combustion": 3896.0163973633753
        },
        "killsBySource": {
          "atmospheric_exposure": 0,
          "surface_corrosion": 0,
          "thermal_exposure": 3,
          "catastrophic_overpressure": 0,
          "radiation_field": 0,
          "hydrogen_oxygen_combustion": 25
        },
        "levelId": "flash_point",
        "round": 5
      }
    ]
  },
  "make_the_reagent": {
    "terminalPhase": "level_complete",
    "reports": [
      {
        "spawned": 5,
        "killed": 5,
        "breached": 0,
        "coreDamage": 0,
        "damageDealt": 84.08398428255734,
        "reactions": 14.834074962733537,
        "combustionFlashes": 0,
        "peakHazard": 100,
        "matterHarvested": 10,
        "fieldDamageAbsorbed": 0,
        "reagentEmitted": 0,
        "armorTransitions": 0,
        "protectedAllySeconds": 0,
        "damageByChannel": {
          "atmosphere": 52.25692135358897,
          "corrosion": 31.827062928968388,
          "heat": 0,
          "pressure": 0,
          "radiation": 0
        },
        "damageBySource": {
          "atmospheric_exposure": 52.25692135358897,
          "surface_corrosion": 31.827062928968388,
          "thermal_exposure": 0,
          "catastrophic_overpressure": 0,
          "radiation_field": 0,
          "hydrogen_oxygen_combustion": 0
        },
        "killsBySource": {
          "atmospheric_exposure": 5,
          "surface_corrosion": 0,
          "thermal_exposure": 0,
          "catastrophic_overpressure": 0,
          "radiation_field": 0,
          "hydrogen_oxygen_combustion": 0
        },
        "levelId": "make_the_reagent",
        "round": 1
      },
      {
        "spawned": 9,
        "killed": 9,
        "breached": 0,
        "coreDamage": 0,
        "damageDealt": 544.4999999999998,
        "reactions": 0.1659250372664641,
        "combustionFlashes": 0,
        "peakHazard": 100,
        "matterHarvested": 45,
        "fieldDamageAbsorbed": 0,
        "reagentEmitted": 0,
        "armorTransitions": 0,
        "protectedAllySeconds": 0,
        "damageByChannel": {
          "atmosphere": 309.1445220997658,
          "corrosion": 235.35547790023418,
          "heat": 0,
          "pressure": 0,
          "radiation": 0
        },
        "damageBySource": {
          "atmospheric_exposure": 309.1445220997658,
          "surface_corrosion": 235.35547790023418,
          "thermal_exposure": 0,
          "catastrophic_overpressure": 0,
          "radiation_field": 0,
          "hydrogen_oxygen_combustion": 0
        },
        "killsBySource": {
          "atmospheric_exposure": 9,
          "surface_corrosion": 0,
          "thermal_exposure": 0,
          "catastrophic_overpressure": 0,
          "radiation_field": 0,
          "hydrogen_oxygen_combustion": 0
        },
        "levelId": "make_the_reagent",
        "round": 2
      },
      {
        "spawned": 5,
        "killed": 5,
        "breached": 0,
        "coreDamage": 0,
        "damageDealt": 962.4999999999997,
        "reactions": 4.334262837072362,
        "combustionFlashes": 0,
        "peakHazard": 100,
        "matterHarvested": 45,
        "fieldDamageAbsorbed": 0,
        "reagentEmitted": 0,
        "armorTransitions": 5,
        "protectedAllySeconds": 0,
        "damageByChannel": {
          "atmosphere": 252.650909897914,
          "corrosion": 709.8490901020865,
          "heat": 0,
          "pressure": 0,
          "radiation": 0
        },
        "damageBySource": {
          "atmospheric_exposure": 252.650909897914,
          "surface_corrosion": 709.8490901020865,
          "thermal_exposure": 0,
          "catastrophic_overpressure": 0,
          "radiation_field": 0,
          "hydrogen_oxygen_combustion": 0
        },
        "killsBySource": {
          "atmospheric_exposure": 0,
          "surface_corrosion": 5,
          "thermal_exposure": 0,
          "catastrophic_overpressure": 0,
          "radiation_field": 0,
          "hydrogen_oxygen_combustion": 0
        },
        "levelId": "make_the_reagent",
        "round": 3
      },
      {
        "spawned": 8,
        "killed": 8,
        "breached": 0,
        "coreDamage": 0,
        "damageDealt": 615.9999999999999,
        "reactions": 1.1623637822519652,
        "combustionFlashes": 0,
        "peakHazard": 100,
        "matterHarvested": 45,
        "fieldDamageAbsorbed": 0,
        "reagentEmitted": 0,
        "armorTransitions": 0,
        "protectedAllySeconds": 0,
        "damageByChannel": {
          "atmosphere": 359.6332108079322,
          "corrosion": 256.36678919206776,
          "heat": 0,
          "pressure": 0,
          "radiation": 0
        },
        "damageBySource": {
          "atmospheric_exposure": 359.6332108079322,
          "surface_corrosion": 256.36678919206776,
          "thermal_exposure": 0,
          "catastrophic_overpressure": 0,
          "radiation_field": 0,
          "hydrogen_oxygen_combustion": 0
        },
        "killsBySource": {
          "atmospheric_exposure": 8,
          "surface_corrosion": 0,
          "thermal_exposure": 0,
          "catastrophic_overpressure": 0,
          "radiation_field": 0,
          "hydrogen_oxygen_combustion": 0
        },
        "levelId": "make_the_reagent",
        "round": 4
      },
      {
        "spawned": 15,
        "killed": 15,
        "breached": 0,
        "coreDamage": 0,
        "damageDealt": 1567.499999999999,
        "reactions": 1.6109241267079735,
        "combustionFlashes": 0,
        "peakHazard": 100,
        "matterHarvested": 100,
        "fieldDamageAbsorbed": 203.83,
        "reagentEmitted": 5.81999999999999,
        "armorTransitions": 4,
        "protectedAllySeconds": 10.999999999999991,
        "damageByChannel": {
          "atmosphere": 643.1358651652592,
          "corrosion": 924.3641348347398,
          "heat": 0,
          "pressure": 0,
          "radiation": 0
        },
        "damageBySource": {
          "atmospheric_exposure": 643.1358651652592,
          "surface_corrosion": 924.3641348347398,
          "thermal_exposure": 0,
          "catastrophic_overpressure": 0,
          "radiation_field": 0,
          "hydrogen_oxygen_combustion": 0
        },
        "killsBySource": {
          "atmospheric_exposure": 9,
          "surface_corrosion": 6,
          "thermal_exposure": 0,
          "catastrophic_overpressure": 0,
          "radiation_field": 0,
          "hydrogen_oxygen_combustion": 0
        },
        "levelId": "make_the_reagent",
        "round": 5
      }
    ]
  },
  "stored_chlorine": {
    "terminalPhase": "level_complete",
    "reports": [
      {
        "spawned": 4,
        "killed": 4,
        "breached": 0,
        "coreDamage": 0,
        "damageDealt": 411.40000000000015,
        "reactions": 36.950852821083636,
        "combustionFlashes": 0,
        "peakHazard": 100,
        "matterHarvested": 24,
        "fieldDamageAbsorbed": 0,
        "reagentEmitted": 0,
        "armorTransitions": 0,
        "protectedAllySeconds": 0,
        "damageByChannel": {
          "atmosphere": 168.46798691172225,
          "corrosion": 239.8937309862812,
          "heat": 3.03828210199683,
          "pressure": 0,
          "radiation": 0
        },
        "damageBySource": {
          "atmospheric_exposure": 168.46798691172225,
          "surface_corrosion": 239.8937309862812,
          "thermal_exposure": 3.03828210199683,
          "catastrophic_overpressure": 0,
          "radiation_field": 0,
          "hydrogen_oxygen_combustion": 0
        },
        "killsBySource": {
          "atmospheric_exposure": 0,
          "surface_corrosion": 4,
          "thermal_exposure": 0,
          "catastrophic_overpressure": 0,
          "radiation_field": 0,
          "hydrogen_oxygen_combustion": 0
        },
        "levelId": "stored_chlorine",
        "round": 1
      },
      {
        "spawned": 5,
        "killed": 5,
        "breached": 0,
        "coreDamage": 0,
        "damageDealt": 949.8500000000001,
        "reactions": 106.25742981121962,
        "combustionFlashes": 0,
        "peakHazard": 100,
        "matterHarvested": 52,
        "fieldDamageAbsorbed": 0,
        "reagentEmitted": 0,
        "armorTransitions": 3,
        "protectedAllySeconds": 0,
        "damageByChannel": {
          "atmosphere": 123.34123985776024,
          "corrosion": 795.1767109066006,
          "heat": 3.3396136075740186,
          "pressure": 27.992435628064246,
          "radiation": 0
        },
        "damageBySource": {
          "atmospheric_exposure": 123.34123985776024,
          "surface_corrosion": 795.1767109066006,
          "thermal_exposure": 3.3396136075740186,
          "catastrophic_overpressure": 27.992435628064246,
          "radiation_field": 0,
          "hydrogen_oxygen_combustion": 0
        },
        "killsBySource": {
          "atmospheric_exposure": 0,
          "surface_corrosion": 4,
          "thermal_exposure": 0,
          "catastrophic_overpressure": 1,
          "radiation_field": 0,
          "hydrogen_oxygen_combustion": 0
        },
        "levelId": "stored_chlorine",
        "round": 2
      },
      {
        "spawned": 8,
        "killed": 4,
        "breached": 4,
        "coreDamage": 42,
        "damageDealt": 370.17694510117377,
        "reactions": 37.42012400165648,
        "combustionFlashes": 0,
        "peakHazard": 100,
        "matterHarvested": 24,
        "fieldDamageAbsorbed": 0,
        "reagentEmitted": 12.00000000000003,
        "armorTransitions": 0,
        "protectedAllySeconds": 0,
        "damageByChannel": {
          "atmosphere": 102.38585064685903,
          "corrosion": 262.10582940687607,
          "heat": 5.68526504743803,
          "pressure": 0,
          "radiation": 0
        },
        "damageBySource": {
          "atmospheric_exposure": 102.38585064685903,
          "surface_corrosion": 262.10582940687607,
          "thermal_exposure": 5.68526504743803,
          "catastrophic_overpressure": 0,
          "radiation_field": 0,
          "hydrogen_oxygen_combustion": 0
        },
        "killsBySource": {
          "atmospheric_exposure": 0,
          "surface_corrosion": 4,
          "thermal_exposure": 0,
          "catastrophic_overpressure": 0,
          "radiation_field": 0,
          "hydrogen_oxygen_combustion": 0
        },
        "levelId": "stored_chlorine",
        "round": 3
      },
      {
        "spawned": 7,
        "killed": 7,
        "breached": 0,
        "coreDamage": 0,
        "damageDealt": 1197.8999999999978,
        "reactions": 21.520002047215467,
        "combustionFlashes": 0,
        "peakHazard": 100,
        "matterHarvested": 72,
        "fieldDamageAbsorbed": 236.8007408181501,
        "reagentEmitted": 0,
        "armorTransitions": 3,
        "protectedAllySeconds": 55.69999999999997,
        "damageByChannel": {
          "atmosphere": 297.8407173509479,
          "corrosion": 897.3651004212111,
          "heat": 2.6941822278382066,
          "pressure": 0,
          "radiation": 0
        },
        "damageBySource": {
          "atmospheric_exposure": 297.8407173509479,
          "surface_corrosion": 897.3651004212111,
          "thermal_exposure": 2.6941822278382066,
          "catastrophic_overpressure": 0,
          "radiation_field": 0,
          "hydrogen_oxygen_combustion": 0
        },
        "killsBySource": {
          "atmospheric_exposure": 1,
          "surface_corrosion": 6,
          "thermal_exposure": 0,
          "catastrophic_overpressure": 0,
          "radiation_field": 0,
          "hydrogen_oxygen_combustion": 0
        },
        "levelId": "stored_chlorine",
        "round": 4
      },
      {
        "spawned": 13,
        "killed": 13,
        "breached": 0,
        "coreDamage": 0,
        "damageDealt": 1337.0500000000006,
        "reactions": 7.010280155267762,
        "combustionFlashes": 1,
        "peakHazard": 100,
        "matterHarvested": 97,
        "fieldDamageAbsorbed": 142.15763175421912,
        "reagentEmitted": 8.339999999999979,
        "armorTransitions": 2,
        "protectedAllySeconds": 10.899999999999993,
        "damageByChannel": {
          "atmosphere": 150.79637189245958,
          "corrosion": 716.1099875062268,
          "heat": 13.493359068376222,
          "pressure": 456.65028153293815,
          "radiation": 0
        },
        "damageBySource": {
          "atmospheric_exposure": 150.79637189245958,
          "surface_corrosion": 716.1099875062268,
          "thermal_exposure": 4.208239732590334,
          "catastrophic_overpressure": 0,
          "radiation_field": 0,
          "hydrogen_oxygen_combustion": 465.935400868724
        },
        "killsBySource": {
          "atmospheric_exposure": 2,
          "surface_corrosion": 3,
          "thermal_exposure": 0,
          "catastrophic_overpressure": 0,
          "radiation_field": 0,
          "hydrogen_oxygen_combustion": 8
        },
        "levelId": "stored_chlorine",
        "round": 5
      }
    ]
  },
  "commissioning_exam": {
    "terminalPhase": "victory",
    "reports": [
      {
        "spawned": 5,
        "killed": 5,
        "breached": 0,
        "coreDamage": 0,
        "damageDealt": 565.6750000000001,
        "reactions": 90.66674661747398,
        "combustionFlashes": 0,
        "peakHazard": 100,
        "matterHarvested": 30,
        "fieldDamageAbsorbed": 0,
        "reagentEmitted": 0,
        "armorTransitions": 0,
        "protectedAllySeconds": 0,
        "damageByChannel": {
          "atmosphere": 231.67005931461875,
          "corrosion": 329.8917254583154,
          "heat": 4.113215227066339,
          "pressure": 0,
          "radiation": 0
        },
        "damageBySource": {
          "atmospheric_exposure": 231.67005931461875,
          "surface_corrosion": 329.8917254583154,
          "thermal_exposure": 4.113215227066339,
          "catastrophic_overpressure": 0,
          "radiation_field": 0,
          "hydrogen_oxygen_combustion": 0
        },
        "killsBySource": {
          "atmospheric_exposure": 0,
          "surface_corrosion": 5,
          "thermal_exposure": 0,
          "catastrophic_overpressure": 0,
          "radiation_field": 0,
          "hydrogen_oxygen_combustion": 0
        },
        "levelId": "commissioning_exam",
        "round": 1
      },
      {
        "spawned": 7,
        "killed": 5,
        "breached": 2,
        "coreDamage": 20,
        "damageDealt": 538.9359374151885,
        "reactions": 182.6429497581698,
        "combustionFlashes": 0,
        "peakHazard": 100,
        "matterHarvested": 32,
        "fieldDamageAbsorbed": 0,
        "reagentEmitted": 0,
        "armorTransitions": 0,
        "protectedAllySeconds": 0,
        "damageByChannel": {
          "atmosphere": 219.72282312924264,
          "corrosion": 304.9941645877578,
          "heat": 14.21894969818791,
          "pressure": 0,
          "radiation": 0
        },
        "damageBySource": {
          "atmospheric_exposure": 219.72282312924264,
          "surface_corrosion": 304.9941645877578,
          "thermal_exposure": 14.21894969818791,
          "catastrophic_overpressure": 0,
          "radiation_field": 0,
          "hydrogen_oxygen_combustion": 0
        },
        "killsBySource": {
          "atmospheric_exposure": 0,
          "surface_corrosion": 5,
          "thermal_exposure": 0,
          "catastrophic_overpressure": 0,
          "radiation_field": 0,
          "hydrogen_oxygen_combustion": 0
        },
        "levelId": "commissioning_exam",
        "round": 2
      },
      {
        "spawned": 5,
        "killed": 5,
        "breached": 0,
        "coreDamage": 0,
        "damageDealt": 971.6300000000007,
        "reactions": 134.39915976645753,
        "combustionFlashes": 0,
        "peakHazard": 100,
        "matterHarvested": 51,
        "fieldDamageAbsorbed": 210.4908926226261,
        "reagentEmitted": 0,
        "armorTransitions": 3,
        "protectedAllySeconds": 5.8999999999999995,
        "damageByChannel": {
          "atmosphere": 132.9344256033512,
          "corrosion": 522.927103077185,
          "heat": 0,
          "pressure": 315.76847131946425,
          "radiation": 0
        },
        "damageBySource": {
          "atmospheric_exposure": 132.9344256033512,
          "surface_corrosion": 522.927103077185,
          "thermal_exposure": 0,
          "catastrophic_overpressure": 315.76847131946425,
          "radiation_field": 0,
          "hydrogen_oxygen_combustion": 0
        },
        "killsBySource": {
          "atmospheric_exposure": 0,
          "surface_corrosion": 4,
          "thermal_exposure": 0,
          "catastrophic_overpressure": 1,
          "radiation_field": 0,
          "hydrogen_oxygen_combustion": 0
        },
        "levelId": "commissioning_exam",
        "round": 3
      },
      {
        "spawned": 12,
        "killed": 12,
        "breached": 0,
        "coreDamage": 0,
        "damageDealt": 1477.410000000001,
        "reactions": 63.125662119376805,
        "combustionFlashes": 0,
        "peakHazard": 100,
        "matterHarvested": 92,
        "fieldDamageAbsorbed": 258.85288,
        "reagentEmitted": 0.004491266678577688,
        "armorTransitions": 3,
        "protectedAllySeconds": 7.199999999999998,
        "damageByChannel": {
          "atmosphere": 304.71924761152115,
          "corrosion": 608.6138432203209,
          "heat": 0,
          "pressure": 564.0769091681587,
          "radiation": 0
        },
        "damageBySource": {
          "atmospheric_exposure": 304.71924761152115,
          "surface_corrosion": 608.6138432203209,
          "thermal_exposure": 0,
          "catastrophic_overpressure": 564.0769091681587,
          "radiation_field": 0,
          "hydrogen_oxygen_combustion": 0
        },
        "killsBySource": {
          "atmospheric_exposure": 4,
          "surface_corrosion": 4,
          "thermal_exposure": 0,
          "catastrophic_overpressure": 4,
          "radiation_field": 0,
          "hydrogen_oxygen_combustion": 0
        },
        "levelId": "commissioning_exam",
        "round": 4
      },
      {
        "spawned": 15,
        "killed": 15,
        "breached": 0,
        "coreDamage": 0,
        "damageDealt": 2109.635,
        "reactions": 48.453193968679365,
        "combustionFlashes": 0,
        "peakHazard": 100,
        "matterHarvested": 125,
        "fieldDamageAbsorbed": 240.52501000000007,
        "reagentEmitted": 0.00037552612939606433,
        "armorTransitions": 3,
        "protectedAllySeconds": 7.100000000000001,
        "damageByChannel": {
          "atmosphere": 516.8762196496858,
          "corrosion": 755.3945264102409,
          "heat": 0,
          "pressure": 837.3642539400735,
          "radiation": 0
        },
        "damageBySource": {
          "atmospheric_exposure": 516.8762196496858,
          "surface_corrosion": 755.3945264102409,
          "thermal_exposure": 0,
          "catastrophic_overpressure": 837.3642539400735,
          "radiation_field": 0,
          "hydrogen_oxygen_combustion": 0
        },
        "killsBySource": {
          "atmospheric_exposure": 5,
          "surface_corrosion": 4,
          "thermal_exposure": 0,
          "catastrophic_overpressure": 6,
          "radiation_field": 0,
          "hydrogen_oxygen_combustion": 0
        },
        "levelId": "commissioning_exam",
        "round": 5
      }
    ]
  }
}
